{
  "last_updated": "2026-05-30 05:30:01",
  "server_uptime_seconds": 5491720,
  "server_open_count": 196,
  "players": [
    {
      "name": "F1ku2376",
      "xuid": "2535459849782491",
      "playtime_seconds": 368758,
      "join_count": 221,
      "last_seen": "2026-05-28 18:40:58"
    },
    {
      "name": "Penbas1675",
      "xuid": "2535412868977356",
      "playtime_seconds": 305940,
      "join_count": 92,
      "last_seen": "2026-05-24 13:08:43"
    },
    {
      "name": "Remonedo1882",
      "xuid": "2535442245226493",
      "playtime_seconds": 642819,
      "join_count": 100,
      "last_seen": "2026-05-30 04:32:09"
    },
    {
      "name": "kamonohashi123",
      "xuid": "2535426609617963",
      "playtime_seconds": 299789,
      "join_count": 92,
      "last_seen": "2026-05-24 17:27:54"
    },
    {
      "name": "NEKOMARU 119",
      "xuid": "2535455351900966",
      "playtime_seconds": 53210,
      "join_count": 16,
      "last_seen": "2026-05-29 19:11:50"
    },
    {
      "name": "RustyDrake3638",
      "xuid": "2535417070048526",
      "playtime_seconds": 832,
      "join_count": 2,
      "last_seen": "2026-04-04 23:00:16"
    },
    {
      "name": "zenless zero0",
      "xuid": "2535415842750871",
      "playtime_seconds": 1723,
      "join_count": 1,
      "last_seen": "2026-04-11 23:28:39"
    }
  ]
}